[
    {
        "id": "2ccf",
        "c_name": "Special batch",
        "c_desc": null,
        "c_number": "8834",
        "c_selected": "919344025402,9514687174,9514687174",
        "active_status": "true",
        "selectedOptions": [
            "4dd3",
            "576e",
            "8834"
        ]
    },
    {
        "c_name": "new ar 23 not",
        "c_desc": null,
        "c_number": "f982",
        "c_selected": "fasfdasdf,2,9080530585",
        "active_status": "true",
        "selectedOptions": [
            "3",
            "1",
            "f982"
        ],
        "id": "0"
    },
    {
        "c_name": "not",
        "c_desc": null,
        "c_number": "f982",
        "c_selected": "afsdfa,2,9080530585",
        "active_status": "true",
        "selectedOptions": [
            "2",
            "1",
            "f982"
        ],
        "id": "1"
    },
    {
        "c_name": "gan",
        "c_desc": null,
        "c_number": "4",
        "c_selected": "7338908955",
        "active_status": "true",
        "selectedOptions": [
            "4"
        ],
        "id": "3"
    }
]